timeseries_preprocess/__init__.py
timeseries_preprocess/timeseries_preprocess_framework.py
timeseries_preprocess/denoise/__init__.py
timeseries_preprocess/denoise/adaptive_denoise.py
timeseries_preprocess/denoise/ceemdan_denoise.py
timeseries_preprocess/denoise/denoise_object.py
timeseries_preprocess/denoise/eemd_denoise.py
timeseries_preprocess/denoise/emd_denoise.py
timeseries_preprocess/denoise/fourier_denoise.py
timeseries_preprocess/denoise/moving_avg_denoise.py
timeseries_preprocess/denoise/moving_median_denoise.py
timeseries_preprocess/denoise/ssa_denoise.py
timeseries_preprocess/imputation/__init__.py
timeseries_preprocess/imputation/backward_imputation.py
timeseries_preprocess/imputation/fixed_value_imputation.py
timeseries_preprocess/imputation/forward_imputation.py
timeseries_preprocess/imputation/imputation_object.py
timeseries_preprocess/imputation/interpolate_imputation.py
timeseries_preprocess/imputation/knn_imputation.py
timeseries_preprocess/imputation/mean_imputation.py
timeseries_preprocess/imputation/median_imputation.py
timeseries_preprocess/imputation/missing_forest_imputation.py
timeseries_preprocess/imputation/mode_imputation.py
timeseries_preprocess/imputation/moving_avg_imputation.py
timeseries_preprocess/imputation/weighted_moving_avg_imputation.py
timeseries_preprocess/outlier/__init__.py
timeseries_preprocess/outlier/dbscan_outlier.py
timeseries_preprocess/outlier/gesd_outlier.py
timeseries_preprocess/outlier/iqr_outlier.py
timeseries_preprocess/outlier/kmeans_outlier.py
timeseries_preprocess/outlier/outlier_object.py
timeseries_preprocess/tests/__init__.py
timeseries_preprocess/utils/__init__.py
Timeseries_Preprocess-0.1.3.dist-info/LICENSE
Timeseries_Preprocess-0.1.3.dist-info/METADATA
Timeseries_Preprocess-0.1.3.dist-info/WHEEL
Timeseries_Preprocess-0.1.3.dist-info/top_level.txt
Timeseries_Preprocess-0.1.3.dist-info/RECORD
