Metadata-Version: 2.1
Name: Timeseries-Preprocess
Version: 0.1.3
Summary: toolkit for time series preprocessing
Home-page: https://github.com/Kiko-RWan/Timeseries-Preprocess
Author: Rui Wan
Author-email: rwan972000@gamil.com
License: MIT
Platform: UNKNOWN
Requires-Dist: numpy
Requires-Dist: pandas
Requires-Dist: EMD-signal
Requires-Dist: scikit-learn
Requires-Dist: missingpy
